src/__init__.py
src/cli.py
desbordante_cli-1.1.1.dist-info/LICENCE
desbordante_cli-1.1.1.dist-info/METADATA
desbordante_cli-1.1.1.dist-info/WHEEL
desbordante_cli-1.1.1.dist-info/entry_points.txt
desbordante_cli-1.1.1.dist-info/RECORD
