Metadata-Version: 2.1
Name: desbordante-cli
Version: 1.1.1
Summary: CLI interface for Desbordante platform
License: AGPL-3.0-or-later
Author: Desbordante Team
Author-email: chernishev@gmail.com
Requires-Python: >=3.11
Classifier: License :: OSI Approved :: GNU Affero General Public License v3 or later (AGPLv3+)
Classifier: Programming Language :: Python :: 3
Classifier: Programming Language :: Python :: 3.11
Classifier: Programming Language :: Python :: 3.12
Requires-Dist: click (>=8.1.7,<9.0.0)
Requires-Dist: desbordante (==2.2.0)
